Topsis_102153035/Topsis_102153035.py
Topsis_102153035/__init__.py
Topsis_102153035/__main__.py
Topsis_102153035-1.0.dist-info/METADATA
Topsis_102153035-1.0.dist-info/WHEEL
Topsis_102153035-1.0.dist-info/entry_points.txt
Topsis_102153035-1.0.dist-info/top_level.txt
Topsis_102153035-1.0.dist-info/RECORD
