Metadata-Version: 2.1
Name: Topsis-102153035
Version: 1.0
Requires-Dist: pandas
Requires-Dist: numpy
Requires-Dist: scikit-learn
